{
  "books": [
    {
      "id": "1",
      "title": "Кухня",
      "author": "Маргарита К.",
      "price": "500",
      "description": "Погружаясь в мир кулинарии: от простых рецептов до высшего кулинарного искусства. Эта книга представляет собой полное погружение в мир кухни – от основных приемов готовки до изысканных рецептов из лучших ресторанов мира. ",
      "image": "../img/book1.png",
      "publishingHouse": "МИФ",
      "year": "2019",
      "pages": "320",
      "binding": "Твердый",
      "weight": "400",
      "size": "20x13x2",
      "ageLimit": "12+",
      "mark": "4.5",
      "navTo": "kitchen",
      "genre": "Кулинария",
      "avatarAutor": "../img/avatar1.png",
      "avatarPublishingHouse": "../img/avatar2.png"
    },
    {
      "id": "2",
      "title": "Раньше девочки носили платья в горошек",
      "author": "Катя М.",
      "price": "175",
      "description": "Мы – поколение девушек, чьи бабушки и мамы носили платья в горошек, – живем в непростое время. Этот переходный период наполнен тревогой, страхом, сомнениями.",
      "image": "../img/book2.png",
      "publishingHouse": "АСТ",
      "year": "2020",
      "pages": "288",
      "binding": "Мягкий",
      "weight": "350",
      "size": "21x14x1.5",
      "ageLimit": "12+",
      "mark": "4.2",
      "navTo": "dresses",
      "genre": "Психология",
      "avatarAutor": "../img/avatar1.png",
      "avatarPublishingHouse": "../img/avatar2.png"
    },
    {
      "id": "3",
      "title": "The storm crown",
      "author": "Kalyn J.",
      "price": "1200",
      "description": "Deep in the heart of Ilucia she must hatch the last crow, hold her own against the crown prince, and ignite a rebellion to take back what is hers.",
      "image": "../img/book3.png",
      "publishingHouse": "Эксмо",
      "year": "2018",
      "pages": "256",
      "binding": "Твердый",
      "weight": "300",
      "size": "20x12x1.8",
      "ageLimit": "18+",
      "mark": "4.7",
      "navTo": "storm",
      "genre": "Фэнтези",
      "avatarAutor": "../img/avatar1.png",
      "avatarPublishingHouse": "../img/avatar2.png"
    },
    {
      "id": "4",
      "title": "Ночной паром в танжер",
      "author": "Кевин Б.",
      "price": "1499",
      "description": "Гангстерское драмеди о любви, взаимных предательствах и вине, полное мрачного юмора и лиризма.",
      "image": "../img/book4.png",
      "publishingHouse": "МИФ",
      "year": "2023",
      "pages": "459",
      "binding": "Твердый",
      "weight": "400",
      "size": "20x12x1.8",
      "ageLimit": "18+",
      "mark": "4.49",
      "navTo": "ferry",
      "genre": "Приключения",
      "avatarAutor": "../img/avatar1.png",
      "avatarPublishingHouse": "../img/avatar2.png"
    },
    {
      "id": "5",
      "title": "Перестаньте угождать людям",
      "author": "Патрик К.",
      "price": "4500",
      "description": "Угодничество не зря называют болезнью. Оно может искалечить вас, заставив забыть о себе в угоду другим людям. Книга «Перестаньте угождать людям» – это откровенный взгляд на склонность угождать... ",
      "image": "../img/book5.png",
      "publishingHouse": "Библос",
      "year": "2022",
      "pages": "147",
      "binding": "Мягкий",
      "weight": "364",
      "size": "24.2x17.2x1.3",
      "ageLimit": "12+",
      "mark": "4.8",
      "navTo": "kitchen",
      "genre": "Психология",
      "avatarAutor": "../img/avatar1.png",
      "avatarPublishingHouse": "../img/avatar2.png"
    },
    {
      "id": "6",
      "title": "Наука чтения людей",
      "author": "Патрик К.",
      "price": "3150",
      "description": "Лучшие рекомендации из поведенческой психологии и как их применять в повседневной жизни. Люди – не такие уж сложные существа, если знать, как они ведут себя в базовом состоянии.",
      "image": "../img/book6.png",
      "publishingHouse": "Библос",
      "year": "2023",
      "pages": "562",
      "binding": "Твердый",
      "weight": "384",
      "size": "24x17x1.4",
      "ageLimit": "16+",
      "mark": "4",
      "navTo": "kitchen",
      "genre": "Психология",
      "avatarAutor": "../img/avatar1.png",
      "avatarPublishingHouse": "../img/avatar2.png"
    },
    {
      "id": "7",
      "title": "Тревожные люди",
      "author": "Фредрик Б.",
      "price": "2899",
      "description": "Однажды утром некий отчаявшийся мужчина средних лет, вооруженный пистолетом, решил ограбить банк, но все пошло не по плану. Вместо банка он попал в дом, выставленный на продажу, а вместо... ",
      "image": "../img/book7.png",
      "publishingHouse": "Синдбад",
      "year": "2018",
      "pages": "416",
      "binding": "Твердый",
      "weight": "426",
      "size": "22x12x4",
      "ageLimit": "18+",
      "mark": "5",
      "navTo": "kitchen",
      "genre": "Роман",
      "avatarAutor": "../img/avatar1.png",
      "avatarPublishingHouse": "../img/avatar2.png"
    }
  ],
  "users": [
    {
      "id": "1",
      "name": "vadim",
      "surname": "saraev",
      "email": "admin@gmail.com",
      "password": "admin"
    }
  ]
}
